_flexfloat.abi3.so
pyflexfloat/util.py
pyflexfloat/build_flexfloat_ffi.py
pyflexfloat/__init__.py
pyflexfloat/FlexFloat.py
pyflexfloat/func.py
pyflexfloat-0.1.2.dist-info/top_level.txt
pyflexfloat-0.1.2.dist-info/METADATA
pyflexfloat-0.1.2.dist-info/WHEEL
pyflexfloat-0.1.2.dist-info/RECORD
pyflexfloat-0.1.2.dist-info/LICENSE
