Metadata-Version: 2.1
Name: pyflexfloat
Version: 0.1.2
Summary: Python wrapper for FlexFloat library
Author-email: Luca Colagrande <luca.colagrande3@gmail.com>
License:                                  Apache License
Requires-Python: >=3.9
License-File: LICENSE
Requires-Dist: cffi
